env/Lib/site-packages/typing_extensions.py
env/Lib/site-packages/_distutils_hack/__init__.py
env/Lib/site-packages/_distutils_hack/override.py
env/Lib/site-packages/backports/__init__.py
env/Lib/site-packages/backports/tarfile/__init__.py
env/Lib/site-packages/backports/tarfile/__main__.py
env/Lib/site-packages/backports/tarfile/compat/__init__.py
env/Lib/site-packages/backports/tarfile/compat/py38.py
env/Lib/site-packages/blinker/__init__.py
env/Lib/site-packages/blinker/_utilities.py
env/Lib/site-packages/blinker/base.py
env/Lib/site-packages/blinker/py.typed
env/Lib/site-packages/build/__init__.py
env/Lib/site-packages/build/__main__.py
env/Lib/site-packages/build/_builder.py
env/Lib/site-packages/build/_ctx.py
env/Lib/site-packages/build/_exceptions.py
env/Lib/site-packages/build/_types.py
env/Lib/site-packages/build/_util.py
env/Lib/site-packages/build/env.py
env/Lib/site-packages/build/py.typed
env/Lib/site-packages/build/util.py
env/Lib/site-packages/build/_compat/__init__.py
env/Lib/site-packages/build/_compat/importlib.py
env/Lib/site-packages/build/_compat/tarfile.py
env/Lib/site-packages/build/_compat/tomllib.py
env/Lib/site-packages/certifi/__init__.py
env/Lib/site-packages/certifi/__main__.py
env/Lib/site-packages/certifi/core.py
env/Lib/site-packages/certifi/py.typed
env/Lib/site-packages/charset_normalizer/__init__.py
env/Lib/site-packages/charset_normalizer/__main__.py
env/Lib/site-packages/charset_normalizer/api.py
env/Lib/site-packages/charset_normalizer/cd.py
env/Lib/site-packages/charset_normalizer/constant.py
env/Lib/site-packages/charset_normalizer/legacy.py
env/Lib/site-packages/charset_normalizer/md.py
env/Lib/site-packages/charset_normalizer/models.py
env/Lib/site-packages/charset_normalizer/py.typed
env/Lib/site-packages/charset_normalizer/utils.py
env/Lib/site-packages/charset_normalizer/version.py
env/Lib/site-packages/charset_normalizer/cli/__init__.py
env/Lib/site-packages/charset_normalizer/cli/__main__.py
machaao_client-0.0.5.dist-info/LICENSE.txt
machaao_client-0.0.5.dist-info/METADATA
machaao_client-0.0.5.dist-info/WHEEL
machaao_client-0.0.5.dist-info/top_level.txt
machaao_client-0.0.5.dist-info/RECORD
