Metadata-Version: 2.1
Name: machaao_client
Version: 0.0.5
Summary: A package for rapidly prototyping a bot on Machaao platform
Author-email: Machaao <sayantan@machaao.com>
License: GNU GENERAL PUBLIC LICENSE
Project-URL: Homepage, https://github.com/machaao/machaao-client
Classifier: Programming Language :: Python :: 3
Classifier: License :: OSI Approved :: GNU General Public License v3 (GPLv3)
Classifier: Operating System :: OS Independent
Requires-Python: >=3.8
License-File: LICENSE.txt
Requires-Dist: PyJWT ==2.9.0
Requires-Dist: python-dotenv ==1.0.1
Requires-Dist: requests ==2.32.3
Requires-Dist: urllib3 ==2.2.3
Requires-Dist: flask ==3.0.3
Requires-Dist: pytz ==2024.2
